ipyearth/__init__.py
ipyearth/_version.py
ipyearth/earth.py
ipyearth/simplify.py
ipyearth/static/extension.js
ipyearth/static/index.js
ipyearth/static/index.js.map
ipyearth-0.1.0a1.data/data/share/jupyter/nbextensions/ipyearth/extension.js
ipyearth-0.1.0a1.data/data/share/jupyter/nbextensions/ipyearth/index.js
ipyearth-0.1.0a1.data/data/share/jupyter/nbextensions/ipyearth/index.js.map
ipyearth-0.1.0a1.dist-info/DESCRIPTION.rst
ipyearth-0.1.0a1.dist-info/METADATA
ipyearth-0.1.0a1.dist-info/RECORD
ipyearth-0.1.0a1.dist-info/WHEEL
ipyearth-0.1.0a1.dist-info/metadata.json
ipyearth-0.1.0a1.dist-info/top_level.txt
