Metadata-Version: 2.0
Name: ipyearth
Version: 0.1.0a1
Summary: An IPython Widget for Earth Maps
Home-page: https://github.com/davidbrochart/ipyearth
Author: David Brochart
Author-email: david.brochart@gmail.com
License: UNKNOWN
Download-URL: https://github.com/davidbrochart/ipyearth/archive/0.1.tar.gz
Keywords: ipython,jupyter,widgets,earth
Platform: UNKNOWN
Classifier: Development Status :: 4 - Beta
Classifier: Framework :: IPython
Classifier: Intended Audience :: Developers
Classifier: Intended Audience :: Science/Research
Classifier: Topic :: Multimedia :: Graphics
Classifier: Programming Language :: Python :: 2
Classifier: Programming Language :: Python :: 2.7
Classifier: Programming Language :: Python :: 3
Classifier: Programming Language :: Python :: 3.3
Classifier: Programming Language :: Python :: 3.4
Classifier: Programming Language :: Python :: 3.5
Requires-Dist: ipywidgets (>=7.0.0)
